setup.py
jayasurya_dsnd/Binomialdistribution.py
jayasurya_dsnd/Gaussiandistribution.py
jayasurya_dsnd/Generaldistribution.py
jayasurya_dsnd/__init__.py
jayasurya_dsnd.egg-info/PKG-INFO
jayasurya_dsnd.egg-info/SOURCES.txt
jayasurya_dsnd.egg-info/dependency_links.txt
jayasurya_dsnd.egg-info/not-zip-safe
jayasurya_dsnd.egg-info/top_level.txt